{
  "metadataAttributes": {
    "title": "EMBARGO",
    "documentId": "BD1-00316",
    "source": "bancoestado",
    "category": "Educacion Financiera",
    "tags": "aprehension,diccionario,educacion-financiera,embargo,figura,finanzas-personales,legal",
    "subcategory": "Diccionario",
    "sourceUrl": "https://www.educacionfinancierabancoestado.cl/herramientas/diccionario",
    "version": "1.0",
    "contentType": "dictionary",
    "wordCount": "39",
    "lastProcessed": "2026-01-26T16:43:45.430289"
  }
}