{
  "metadataAttributes": {
    "title": "DIVISIÓN DE TRABAJO",
    "documentId": "BD1-00308",
    "source": "bancoestado",
    "category": "Educacion Financiera",
    "tags": "diccionario,division,educacion-financiera,finanzas-personales,forma,pasteles,personas,trabajo",
    "subcategory": "Diccionario",
    "sourceUrl": "https://www.educacionfinancierabancoestado.cl/herramientas/diccionario",
    "version": "1.0",
    "contentType": "dictionary",
    "wordCount": "104",
    "lastProcessed": "2026-01-26T16:43:45.422660"
  }
}